embd/__init__.py
embd/bytes.py
embd/embed.py
embd/space.py
embd/types.py
embd/bin/__init__.py
embd/bin/think.py
embd-0.1.5.dist-info/METADATA
embd-0.1.5.dist-info/WHEEL
embd-0.1.5.dist-info/entry_points.txt
embd-0.1.5.dist-info/top_level.txt
embd-0.1.5.dist-info/RECORD
