Metadata-Version: 2.4
Name: embd
Version: 0.1.5
Summary: Unix embedding driver for software 2.0
Author-email: Jason Wilkes <notarealdeveloper@gmail.com>
Project-URL: source, https://github.com/notarealdeveloper/embd
Project-URL: download, https://pypi.org/project/embd/#files
Requires-Dist: pytest
Requires-Dist: sentence_transformers
Requires-Dist: pandas
Requires-Dist: is_instance>=0.0.5
Requires-Dist: assure>=0.0.5
Requires-Dist: mmry>=0.0.5
